README.md
setup.py
display_timedelta/__init__.py
display_timedelta/display.py
display_timedelta.egg-info/PKG-INFO
display_timedelta.egg-info/SOURCES.txt
display_timedelta.egg-info/dependency_links.txt
display_timedelta.egg-info/top_level.txt