Metadata-Version: 2.1
Name: display-timedelta
Version: 1.0
Summary: Displays a timedelta object for human consumption.
Home-page: https://github.com/kavigupta/display-timedelta
Author: Kavi Gupta
Author-email: display_timedelta@kavigupta.org
License: UNKNOWN
Platform: UNKNOWN
Classifier: Programming Language :: Python :: 3.5
Classifier: Programming Language :: Python :: 3.6
Classifier: Programming Language :: Python :: 3.7
Classifier: Programming Language :: Python :: 3.8
Classifier: Operating System :: OS Independent
Requires-Python: >=3.5
